dv_normalize/__init__.py
dv_normalize/dv_numbers.py
dv_normalize/dv_sentence.py
dv_normalize/dv_time.py
dv_normalize/dv_years.py
dv_normalizer-0.1.3.dist-info/LICENCE
dv_normalizer-0.1.3.dist-info/METADATA
dv_normalizer-0.1.3.dist-info/WHEEL
dv_normalizer-0.1.3.dist-info/top_level.txt
dv_normalizer-0.1.3.dist-info/RECORD
