Metadata-Version: 2.1
Name: dv-normalizer
Version: 0.1.3
Summary: A Python library for normalizing Dhivehi text and converting numbers to Dhivehi text format, supporting written, spoken and year forms
Author: Alakxender
Author-email: alakxender@gmail.com
Requires-Python: >=3.8
License-File: LICENCE
